[
  {
    "title": "The Moral Character of Cryptographic Work",
    "site": "IACR Cryptology ePrint Archive",
    "author": "",
    "date": "2024-04-25",
    "timestamp": "2024-04-25T04:39:28.238Z",
    "description": "Cryptography rearranges power: it configures who can do what, from what. This makes cryptography an inherently \\textit{political} tool, and it confers on the field an intrinsically \\textit{moral} dimension. The Snowden revelations motivate a reassessment of the political and moral positioning of cryptography. They lead one to ask if our inability to effectively address mass surveillance constitutes a failure of our field. I believe that it does. I call for a community-wide effort to develop more effective means to resist mass surveillance. I plea for a reinvention of our disciplinary culture to attend not only to puzzles and math, but, also, to the societal implications of our work.",
    "url": "https://eprint.iacr.org/2015/1162",
    "image": "bookmark-the-moral-character-of-cryptographic-work.png",
    "type": "article",
    "tags": [
      "cryptography"
    ],
    "waybackUrl": "http://web.archive.org/web/20240108182637/https://eprint.iacr.org/2015/1162"
  },
  {
    "title": "Ten Signs a Claimed Mathematical Breakthrough is Wrong",
    "site": "Shtetl-Optimized",
    "author": "",
    "date": "2024-04-26",
    "timestamp": "2024-04-26T03:12:58.981Z",
    "description": "Yesterday several people asked my opinion of a preprint claiming to solve the Graph Isomorphism problem in deterministic polynomial time. I responded: If I read all such papers, then I wouldn’t hav…",
    "url": "https://scottaaronson.blog/?p=304",
    "image": "bookmark-ten-signs-a-claimed-mathematical-breakthrough-is-wrong.jpg",
    "type": "article",
    "waybackUrl": "http://web.archive.org/web/20240404220158/https://scottaaronson.blog/?p=304"
  },
  {
    "title": "Rust Language Cheat Sheet",
    "site": "",
    "author": "",
    "date": "2024-04-26",
    "timestamp": "2024-04-26T03:39:03.382Z",
    "description": "",
    "url": "https://cheats.rs/",
    "type": "",
    "tags": [
      "rust"
    ],
    "waybackUrl": "http://web.archive.org/web/20240425090009/https://cheats.rs/"
  },
  {
    "title": "Curated list of awesome lists",
    "site": "",
    "author": "",
    "date": "2024-04-26",
    "timestamp": "2024-04-26T03:44:32.127Z",
    "description": "",
    "url": "https://project-awesome.org/",
    "image": "bookmark-curated-list-of-awesome-lists-project-awesomeorg.png",
    "type": "",
    "waybackUrl": "http://web.archive.org/web/20240414232752/https://project-awesome.org/"
  },
  {
    "title": "finding the right people",
    "site": "",
    "author": "Nix 🕊",
    "date": "2024-04-26",
    "timestamp": "2024-04-26T14:17:27.415Z",
    "description": "Don’t surround yourself with “smarter” people. The trick is to surround yourself with people who are free in ways you’re not. (Ribbonfarm) I’ve been living by this concept before I could consciously articulate it.",
    "url": "https://www.startingfromnix.com/p/finding-the-right-people",
    "image": "bookmark-finding-the-right-people.png",
    "type": "article",
    "waybackUrl": "http://web.archive.org/web/20240417170905/https://www.startingfromnix.com/p/finding-the-right-people"
  },
  {
    "title": "What is PL research and how is it useful? - The PL Enthusiast",
    "site": "The Programming Languages Enthusiast",
    "author": "Michael Hicks",
    "date": "2024-04-28",
    "timestamp": "2024-04-28T23:24:48.853Z",
    "description": "This article looks at what PL research is, at least in part, and why it is effective.",
    "url": "http://www.pl-enthusiast.net/2015/05/27/what-is-pl-research-and-how-is-it-useful/",
    "image": "bookmark-what-is-pl-research-and-how-is-it-useful-the-pl-enthusiast.jpg",
    "type": "article",
    "tags": [
      "pl"
    ],
    "waybackUrl": "http://web.archive.org/web/20240203203027/http://www.pl-enthusiast.net/2015/05/27/what-is-pl-research-and-how-is-it-useful/"
  },
  {
    "title": "Crafting Interpreters",
    "site": "",
    "author": "",
    "date": "2024-04-28",
    "timestamp": "2024-04-28T23:30:14.178Z",
    "description": "",
    "url": "https://craftinginterpreters.com/",
    "type": "",
    "tags": [
      "pl"
    ],
    "waybackUrl": "http://web.archive.org/web/20240415102746/https://www.craftinginterpreters.com/"
  },
  {
    "title": "The Linux Kernel Module Programming Guide",
    "site": "",
    "author": "",
    "date": "2024-04-28",
    "timestamp": "2024-04-28T23:37:37.352Z",
    "description": "",
    "url": "https://sysprog21.github.io/lkmpg/",
    "type": "",
    "waybackUrl": "http://web.archive.org/web/20240211000134/https://sysprog21.github.io/lkmpg/"
  },
  {
    "title": "Authenticated Data Structures (Generically) - The PL Enthusiast",
    "site": "The Programming Languages Enthusiast",
    "author": "Michael Hicks",
    "date": "2024-04-28",
    "timestamp": "2024-04-28T23:49:13.975Z",
    "description": "This blog post is the first in my series on secure computation and will be presented in two parts. It briefly introduces some work my collaborators and I published this year, which illustrates a pleasant application of programming languages ideas to … Continue reading →",
    "url": "http://www.pl-enthusiast.net/2014/06/11/authenticated-data-structures-generically/",
    "image": "bookmark-authenticated-data-structures-generically-the-pl-enthusiast.png",
    "type": "article",
    "tags": [
      "pl",
      "cryptography"
    ],
    "waybackUrl": "http://web.archive.org/web/20240203203041/http://www.pl-enthusiast.net/2014/06/11/authenticated-data-structures-generically/"
  },
  {
    "title": "",
    "site": "",
    "author": "",
    "date": "2024-04-29",
    "timestamp": "2024-04-29T04:14:05.068Z",
    "description": "",
    "url": "https://auerstack.substack.com/p/vladimir-sorokin-meat-and-clones",
    "image": "",
    "type": "",
    "altTitle": "Vladimir Sorokin: Meat and Clones - by David B. Auerbach"
  },
  {
    "title": "",
    "site": "",
    "author": "",
    "date": "2024-04-29",
    "timestamp": "2024-04-29T04:47:08.442Z",
    "description": "",
    "url": "https://sashachapin.substack.com/p/playing-in-the-ruins",
    "image": "",
    "type": "",
    "altTitle": "Playing in the ruins - by Sasha Chapin"
  },
  {
    "title": "playhtml",
    "site": "",
    "author": "",
    "date": "2024-04-29",
    "timestamp": "2024-04-29T21:45:31.822Z",
    "description": "interactive, collaborative html elements with a single attribute",
    "url": "https://playhtml.fun/",
    "image": "bookmark-playhtml.png",
    "type": "",
    "waybackUrl": "http://web.archive.org/web/20231209145843/https://playhtml.fun/",
    "altTitle": "playhtml"
  },
  {
    "title": "On limitations that hide in your blindspot",
    "site": "",
    "author": "Henrik Karlsson",
    "date": "2024-04-29",
    "timestamp": "2024-04-29T21:53:16.761Z",
    "description": "and how to find them",
    "url": "https://www.henrikkarlsson.xyz/p/limitatons",
    "image": "bookmark-on-limitations-that-hide-in-your-blindspot.png",
    "type": "article",
    "waybackUrl": "http://web.archive.org/web/20240408200900/https://www.henrikkarlsson.xyz/p/limitatons",
    "altTitle": "On limitations that hide in your blindspot"
  },
  {
    "title": "djb",
    "site": "",
    "author": "",
    "date": "2024-05-07",
    "timestamp": "2024-05-07T05:04:06.683Z",
    "description": "",
    "url": "http://cr.yp.to/djb.html",
    "type": "",
    "waybackUrl": "http://web.archive.org/web/20240505001012/http://cr.yp.to/djb.html"
  },
  {
    "title": "Marco Cetica",
    "site": "",
    "author": "",
    "date": "2024-05-08",
    "timestamp": "2024-05-08T20:52:04.051Z",
    "description": "Marco Cetica's website",
    "url": "https://marcocetica.com/",
    "type": "",
    "waybackUrl": "http://web.archive.org/web/20240506122930/https://marcocetica.com/",
    "altTitle": "Marco Cetica"
  },
  {
    "title": "[inference labs]",
    "site": "",
    "author": "",
    "date": "2024-05-18",
    "timestamp": "2024-05-18T06:09:34.136Z",
    "description": "Trustless AI running on decentralized systems verified with zero knowledge proofs.",
    "url": "https://inferencelabs.com/",
    "type": "",
    "waybackUrl": "http://web.archive.org/web/20240423204039/https://inferencelabs.com/",
    "altTitle": "[inference labs]"
  },
  {
    "title": "Higher Order Company",
    "site": "",
    "author": "",
    "date": "2024-05-19",
    "timestamp": "2024-05-19T04:40:11.622Z",
    "description": "We're the HOC, a tech startup revolutionizing computing with massively parallel runtimes and processors using our HVM runtime and Bend programming language.",
    "url": "https://higherorderco.com",
    "type": "",
    "altTitle": "Higher Order Company"
  },
  {
    "title": "How to be a Precious Snowflake",
    "site": "ribbonfarm",
    "author": "",
    "date": "2024-06-09",
    "timestamp": "2024-06-09T00:33:17.806Z",
    "description": "Every few months, one of my much more successful friends will get frustrated by my apparent lack of aggressive hustle in service of my own work, and declare that I could be 10x better known and mak…",
    "url": "https://www.ribbonfarm.com/2015/09/17/how-to-be-a-precious-snowflake/",
    "image": "bookmark-how-to-be-a-precious-snowflake.png",
    "type": "article",
    "waybackUrl": "http://web.archive.org/web/20230925064033/https://www.ribbonfarm.com/2015/09/17/how-to-be-a-precious-snowflake/",
    "altTitle": "How to be a Precious Snowflake"
  },
  {
    "title": "Linux Performance Analysis in 60,000 Milliseconds",
    "site": "Medium",
    "author": "Netflix Technology Blog",
    "date": "2024-06-09",
    "timestamp": "2024-06-09T08:20:21.211Z",
    "description": "You log in to a Linux server with a performance issue: what do you check in the first minute?",
    "url": "https://netflixtechblog.com/linux-performance-analysis-in-60-000-milliseconds-accc10403c55",
    "image": "bookmark-linux-performance-analysis-in-60000-milliseconds.png",
    "type": "article",
    "waybackUrl": "http://web.archive.org/web/20240529190815/https://netflixtechblog.com/linux-performance-analysis-in-60-000-milliseconds-accc10403c55",
    "altTitle": "Linux Performance Analysis in 60,000 Milliseconds | by Netflix Technology Blog | Netflix TechBlog"
  },
  {
    "title": "Bottlerocket",
    "site": "",
    "author": "",
    "date": "2024-06-09",
    "timestamp": "2024-06-09T11:41:00.692Z",
    "description": "Bottlerocket is a Linux-based operating system optimized for hosting containers. It’s free and open-source software, developed in the open on GitHub. Bottlerocket is installed on the machine or instance where your containers themselves are running. It is specifically designed to work with your container orchestrator (like Kubernetes) to automate the lifecycle of the containers running in your cluster. Bottlerocket runs in the cloud or in your datacenter.",
    "url": "https://bottlerocket.dev/",
    "type": "website",
    "waybackUrl": "http://web.archive.org/web/20240506235721/https://bottlerocket.dev/",
    "altTitle": "Bottlerocket"
  }
]